LICENSE.md
MANIFEST.in
README.md
setup.py
Dirble_Wrapper.egg-info/PKG-INFO
Dirble_Wrapper.egg-info/SOURCES.txt
Dirble_Wrapper.egg-info/dependency_links.txt
Dirble_Wrapper.egg-info/not-zip-safe
Dirble_Wrapper.egg-info/top_level.txt
dirble_wrapper/__init__.py
dirble_wrapper/dirble_wrapper.py