Metadata-Version: 1.1
Name: Dirble-Wrapper
Version: 0.1.0
Summary: DirbleWrapper is a small program to wrap the dirble api
Home-page: https://github.com/speedy1991/DirbleWrapper
Author: Arthur Holzner
Author-email: arthur.holz.91@gmail.com
License: MIT
Platform: any
Classifier: Development Status :: 4 - Beta
Classifier: Intended Audience :: Developers
Classifier: License :: OSI Approved :: MIT License
Classifier: Operating System :: OS Independent
Classifier: Programming Language :: Python
Classifier: Programming Language :: Python :: 3
Classifier: Topic :: Software Development :: Libraries :: Python Modules
